uPyDOS/PyDOS.py
uPyDOS/__init__.py
uPyDOS/basicpython.py
uPyDOS/blink.py
uPyDOS/boot.py
uPyDOS/cls.py
uPyDOS/code.py
uPyDOS/diff.py
uPyDOS/edit.py
uPyDOS/fileview.py
uPyDOS/fsedit.py
uPyDOS/i2cscan.py
uPyDOS/lcdprint.py
uPyDOS/lcdscroll.py
uPyDOS/main.py
uPyDOS/piano.py
uPyDOS/prtglbvar.py
uPyDOS/pydospins.py
uPyDOS/pye.py
uPyDOS/pye_gen.py
uPyDOS/reboot.py
uPyDOS/rgbblink.py
uPyDOS/rgbrainbow.py
uPyDOS/rgbset.py
uPyDOS/run.py
uPyDOS/sdmount.py
uPyDOS/sdumount.py
uPyDOS/setboard.py
uPyDOS/setenv.py
uPyDOS/sound.py
uPyDOS/tsound.py
uPyDOS/wrap_off.py
uPyDOS/wrap_on.py
uPyDOS/PyBasic/PyBasic.py
uPyDOS/PyBasic/basicdata.py
uPyDOS/PyBasic/basicparser.py
uPyDOS/PyBasic/basictoken.py
uPyDOS/PyBasic/flowsignal.py
uPyDOS/PyBasic/lexer.py
uPyDOS/PyBasic/program.py
uPyDOS/cpython/code.py
uPyDOS/cpython/fs.py
uPyDOS/cpython/main.py
uPyDOS/cpython/runvm.py
uPyDOS/cpython/CytronMPP/lib/cyt_mpp_board.py
uPyDOS/cpython/ESP32/code.py
uPyDOS/cpython/ESP32/cpython_wifi.py
uPyDOS/cpython/ESP32/main.py
uPyDOS/cpython/ESP32/requests_https_circuitpython.py
uPyDOS/cpython/ESP32/wifi_finance.py
uPyDOS/cpython/ESP32/wifi_test.py
uPyDOS/cpython/ESP32/wifi_weather.py
uPyDOS/cpython/NanoConnect/connect_wifi.py
uPyDOS/cpython/NanoConnect/lib/adafruit_esp32spi/__init__.py
uPyDOS/cpython/boardconfigs/pydos_bcfg_adafruit_feather_esp32s2.py
uPyDOS/cpython/boardconfigs/pydos_bcfg_adafruit_feather_rp2040.py
uPyDOS/cpython/boardconfigs/pydos_bcfg_adafruit_itsybitsy_rp2040.py
uPyDOS/cpython/boardconfigs/pydos_bcfg_adafruit_qtpy_esp32c3.py
uPyDOS/cpython/boardconfigs/pydos_bcfg_adafruit_qtpy_esp32s2.py
uPyDOS/cpython/boardconfigs/pydos_bcfg_adafruit_qtpy_rp2040.py
uPyDOS/cpython/boardconfigs/pydos_bcfg_arduino_nano_rp2040_connect.py
uPyDOS/cpython/boardconfigs/pydos_bcfg_cytron_maker_pi_pico.py
uPyDOS/cpython/boardconfigs/pydos_bcfg_cytron_maker_pi_rp2040.py
uPyDOS/cpython/boardconfigs/pydos_bcfg_espressif_esp32s3_devkitc_1_n8r2.py
uPyDOS/cpython/boardconfigs/pydos_bcfg_itsybitsy_nrf52840_express.py
uPyDOS-1.10.dist-info/LICENSE
uPyDOS-1.10.dist-info/METADATA
uPyDOS-1.10.dist-info/WHEEL
uPyDOS-1.10.dist-info/top_level.txt
uPyDOS-1.10.dist-info/RECORD
