Metadata-Version: 2.1
Name: uPyDOS
Version: 1.10
Summary: micro PyDOS - Dos like shell for microcontrollers
Author-email: RetiredWizard <PyDOS@RetiredWizard.com>
License: MIT License        
Project-URL: Homepage, https://github.com/RetiredWizard/PyDOS
Project-URL: Bug Tracker, https://github.com/RetiredWizard/PyDOS/issues
Classifier: Programming Language :: Python :: 3
Classifier: License :: OSI Approved :: MIT License
Classifier: Operating System :: OS Independent
Requires-Python: >=3.7
License-File: LICENSE
